README.md
setup.py
test/testPrint.py
tsjPython/__init__.py
tsjPython/gVal.py
tsjPython/tsjCLI.py
tsjPython/tsjCommonFunc.py
tsjPython/tsjData.py
tsjPython/tsjExcel.py
tsjPython/tsjFileChange.py
tsjPython/tsjGraph.py
tsjPython/tsjParallelism.py
tsjPython/tsjTime.py
tsjPython.egg-info/PKG-INFO
tsjPython.egg-info/SOURCES.txt
tsjPython.egg-info/dependency_links.txt
tsjPython.egg-info/requires.txt
tsjPython.egg-info/top_level.txt