Metadata-Version: 2.1
Name: tsjPython
Version: 0.3.1
Summary: personal code for tsj
Home-page: https://github.com/Kirrito-k423/tsjPython
Author: Shaojie Tan
Author-email: shaojiemike@mail.ustc.edu.cn
License: MIT Licence
Keywords: tsj
Platform: any
